LICENSE
MANIFEST.in
README
setup.py
fault_localization/__init__.py
fault_localization/display.py
fault_localization/localization.py
fault_localization/plugin.py
fault_localization/tracing.py
fault_localization.egg-info/PKG-INFO
fault_localization.egg-info/SOURCES.txt
fault_localization.egg-info/dependency_links.txt
fault_localization.egg-info/entry_points.txt
fault_localization.egg-info/requires.txt
fault_localization.egg-info/top_level.txt