Metadata-Version: 1.1
Name: fault-localization
Version: 0.1.6
Summary: A fault localization tool for Python's pytest testing framework.
Home-page: https://github.com/hchasestevens/fault-localization
Author: H. Chase Stevens
Author-email: chase@chasestevens.com
License: MIT
Platform: any
Classifier: Programming Language :: Python
Classifier: Programming Language :: Python :: 2
Classifier: Programming Language :: Python :: 2.7
Classifier: Programming Language :: Python :: 3
Classifier: Programming Language :: Python :: 3.6
Classifier: Topic :: Software Development :: Libraries :: Python Modules
Classifier: Intended Audience :: Developers
Classifier: Operating System :: OS Independent
Classifier: License :: OSI Approved :: MIT License
